<rpc message-id="103" xmlns="urn:ietf:params:xml:ns:netconf:base:1.0">
<edit-config>
<target>
<running>
</running>
</target>
<config>
 <interfaces xmlns="urn:ietf:params:xml:ns:yang:ietf-interfaces">
    <interface>
        <name>Loopback1</name>
        <description>My first NETCONF loopback by ietf-interfaces</description>
        <type xmlns:ianaift="urn:ietf:params:xml:ns:yang:iana-if-type">ianaift:softwareLoopback</type>
        <ipv4 xmlns="urn:ietf:params:xml:ns:yang:ietf-ip">
            <address>
               <ip>10.1.1.1</ip>
               <netmask>255.255.255.0</netmask>
            </address>
        </ipv4>
    </interface>
 </interfaces>
</config>
</edit-config>
</rpc>
]]>]]>

<rpc message-id="103" xmlns="urn:ietf:params:xml:ns:netconf:base:1.0">
<edit-config>
<target>
<running>
</running>
</target>
<config>
 <interfaces xmlns="urn:ietf:params:xml:ns:yang:ietf-interfaces">
    <interface>
        <name>Loopback2</name>
        <description>My second NETCONF loopback by ietf-interfaces</description>
        <type xmlns:ianaift="urn:ietf:params:xml:ns:yang:iana-if-type">ianaift:softwareLoopback</type>
        <ipv4 xmlns="urn:ietf:params:xml:ns:yang:ietf-ip">
            <address>
               <ip>10.1.1.1</ip>
               <netmask>255.255.255.0</netmask>
            </address>
        </ipv4>
    </interface>
 </interfaces>
</config>
</edit-config>
</rpc>
]]>]]>

